examAnalyzerINF219v23/__init__.py
examAnalyzerINF219v23/flash.py
examAnalyzerINF219v23/classes/Constants.py
examAnalyzerINF219v23/classes/File_gen.py
examAnalyzerINF219v23/classes/__init__.py
examAnalyzerINF219v23/classes/features/Box.py
examAnalyzerINF219v23/classes/features/GradeDistribution.py
examAnalyzerINF219v23/classes/features/PBC.py
examAnalyzerINF219v23/classes/features/QuestionTable.py
examAnalyzerINF219v23/classes/features/QuestionTimeAverage.py
examAnalyzerINF219v23/classes/features/TaskDuration.py
examAnalyzerINF219v23/classes/features/__init__.py
examAnalyzerINF219v23/classes/json/Exam.py
examAnalyzerINF219v23/classes/json/Question.py
examAnalyzerINF219v23/classes/json/Result.py
examAnalyzerINF219v23/classes/json/ResultWrapper.py
examAnalyzerINF219v23/classes/json/__init__.py
examAnalyzerINF219v23/templates/index.html
examAnalyserINF219v23-0.1.15.dist-info/LICENSE
examAnalyserINF219v23-0.1.15.dist-info/METADATA
examAnalyserINF219v23-0.1.15.dist-info/WHEEL
examAnalyserINF219v23-0.1.15.dist-info/top_level.txt
examAnalyserINF219v23-0.1.15.dist-info/RECORD
