Metadata-Version: 2.1
Name: examAnalyserINF219v23
Version: 0.1.15
Summary: Exam analyzer
Author: premeide
Author-email: premeide@gmail.com
Keywords: python,education,exam analysis
Classifier: Development Status :: 1 - Planning
Classifier: Intended Audience :: Developers
Classifier: Programming Language :: Python :: 3
Classifier: Operating System :: Unix
Classifier: Operating System :: MacOS :: MacOS X
Classifier: Operating System :: Microsoft :: Windows
License-File: LICENSE
Requires-Dist: Flask
